textural_image_features/__init__.py
textural_image_features/features_extractor.py
textural_image_features/gtsdmatrix.py
textural_image_features/miscellaneous.py
textural_image_features-0.1.0.dist-info/METADATA
textural_image_features-0.1.0.dist-info/WHEEL
textural_image_features-0.1.0.dist-info/RECORD
