Metadata-Version: 2.1
Name: textural-image-features
Version: 0.1.0
Summary: 
Author: Mihajlo Madic
Author-email: mihajlo.madic@elfak.rs
Requires-Python: >=3.10,<3.13
Classifier: Programming Language :: Python :: 3
Classifier: Programming Language :: Python :: 3.10
Classifier: Programming Language :: Python :: 3.11
Requires-Dist: cachetools (>=5.3.2,<6.0.0)
Requires-Dist: matplotlib (>=3.8.1,<4.0.0)
Requires-Dist: numpy (>=1.26.1,<2.0.0)
Requires-Dist: pytest (>=7.4.3,<8.0.0)
